act/__init__.py
act/act_utils.py
act/constants.py
act/convert_ee.py
act/ee_sim_env.py
act/imitate_episodes.py
act/policy.py
act/record_sim_episodes.py
act/scripted_policy.py
act/sim_env.py
act/visualize_episodes.py
diffusion_policy/__init__.py
diffusion_policy/demo_real_robot.py
diffusion_policy/eval_real_robot.py
diffusion_policy/multirun_metrics.py
diffusion_policy/ray_exec.py
diffusion_policy/ray_train_multirun.py
diffusion_policy/setup.py
diffusion_policy/train.py
diffusion_policy/diffusion_policy/__init__.py
utils/__init__.py
utils/act_eval_sweep.py
utils/robomimic_convert_action.py
utils/robomimic_save_waypoints.py
utils/robomimic_visualize_waypoint.py
utils/utils.py
waypoint_extraction/__init__.py
waypoint_extraction/run.py
waypoint_extraction/traj_reconstruction.py
waypoint_extraction-0.1.dist-info/METADATA
waypoint_extraction-0.1.dist-info/WHEEL
waypoint_extraction-0.1.dist-info/top_level.txt
waypoint_extraction-0.1.dist-info/RECORD
