Metadata-Version: 2.1
Name: waypoint-extraction
Version: 0.1
Summary: research project
Home-page: 
Author: IRIS
License: MIT License
Keywords: Deep Learning,Machine Learning
Classifier: Development Status :: 5 - Production/Stable
Classifier: Topic :: Scientific/Engineering :: Artificial Intelligence
Classifier: Environment :: Console
Classifier: Programming Language :: Python :: 3.9
Requires-Python: >=3.6
Requires-Dist: torch
Requires-Dist: torchvision
Requires-Dist: mujoco-py
Requires-Dist: tqdm
Requires-Dist: wandb
Requires-Dist: ipdb
Requires-Dist: numpy (>=1.20.0)
Requires-Dist: numba (>=0.52.0)
Requires-Dist: scipy (>=1.2.3)
Requires-Dist: matplotlib
Requires-Dist: moviepy
Requires-Dist: imageio
Requires-Dist: opencv-python
